{
	"Window": {
		"Toolbar": false,
		"Statusbar": true,
		"Category": true,
		"Summary": false,
		"Banner": false,
		"x": 312,
		"y": 204,
		"width": 715,
		"height": 360,
		"maximized": true,
		"NthCategory": 0,
		"NthStatus": 0,
		"PanedPositionH": 167,
		"PanedPositionV": 547
	},
	"Summary": {
		"name": true,
		"folder": true,
		"category": false,
		"uri": false,
		"message": true
	},
	"DownloadColumn": {
		"complete": false,
		"total": true,
		"percent": true,
		"elapsed": false,
		"left": false,
		"speed": true,
		"UploadSpeed": false,
		"uploaded": false,
		"ratio": false,
		"retry": false,
		"category": false,
		"uri": false,
		"AddedOn": true,
		"CompletedOn": false,
		"SortType": 1,
		"SortNth": 14,
		"Width": {
			"state": 18,
			"name": 180,
			"complete": 0,
			"total": 70,
			"percent": 60,
			"elapsed": 0,
			"left": 0,
			"speed": 80,
			"UploadSpeed": 0,
			"uploaded": 0,
			"ratio": 0,
			"retry": 0,
			"category": 0,
			"uri": 0,
			"AddedOn": 140,
			"CompletedOn": 0
		},
		"completed": false
	},
	"UserInterface": {
		"ExitConfirmation": true,
		"DeleteConfirmation": true,
		"ShowTrayIcon": true,
		"StartInTray": true,
		"CloseToTray": true,
		"StartInOfflineMode": false,
		"StartNotification": true,
		"SoundNotification": true,
		"ApplyRecently": false,
		"ApplyRecent": false,
		"SkipExisting": true,
		"LargeIcon": false
	},
	"Clipboard": {
		"pattern": "avi|mov|m4v|mpg|mpeg|flv|mkv|wmv|mp4|7z|zip|rar|doc|docx|xls|xlsx|odt|odf|css|html|djvu|rtf|csv|tsv|pdf|epub|azw|kf8|css|csv|djvu|vcf|md|mp3|midi|mod|s3m|wav|ogg|m3u|pls|flac|ape|m4a|apk|pup|pet|ebuild|appx|appxbundle|deb|rpm|yum|msi|bin|exe|torrent|metalink|iso|img|cue|",
		"monitor": false,
		"quiet": true,
		"NthCategory": 0,
		"Website": true,
		"MediaWebsite": true
	},
	"Bandwidth": {
		"NormalUpload": 0,
		"NormalDownload": 0,
		"SchedulerUpload": 0,
		"SchedulerDownload": 0
	},
	"Commandline": {
		"quiet": false,
		"NthCategory": 0
	},
	"PluginOrder": 3,
	"PluginAria2": {
		"launch": true,
		"shutdown": true,
		"token": null,
		"path": "aria2c",
		"arguments": "--enable-rpc=true -D --disable-ipv6 --check-certificate=false",
		"uri": "http:\/\/localhost:6800\/jsonrpc",
		"MaxUploadSpeed": 25,
		"MaxDownloadSpeed": 0
	},
	"PluginMedia": {
		"match_mode": 3,
		"quality": 3,
		"type": 0
	},
	"Completion": {
		"remember": true,
		"action": 0,
		"command": null,
		"OnError": null
	},
	"FolderHistory": [
		"\/mnt\/01D4747136A4BF40\/Libraries\/Downloads\/Organized Download\/Video\/Unsorted",
		"\/mnt\/01D4747136A4BF40\/Libraries\/Downloads\/Organized Download\/Compressed",
		"\/mnt\/01D4747136A4BF40\/Libraries\/Downloads\/Organized Download\/Unsorted",
		"\/mnt\/01D4747136A4BF40\/Libraries\/Downloads\/Organized Download\/Programs",
		"\/mnt\/01D4747136A4BF40\/Libraries\/Downloads\/Organized Download\/Music",
		"\/mnt\/01D4747136A4BF40\/Libraries\/Downloads\/Organized Download\/Documents",
		"\/home\/dimmed\/Downloads\/Chrome",
		"\/mnt\/01D474713ACAC240\/Gaki no Tsukai"
	],
	"AutoSave": 1,
	"AutoSaveInterval": 3,
	"Scheduler": {
		"enable": false,
		"state": [
			3,
			3,
			3,
			3,
			3,
			3,
			3,
			0,
			0,
			0,
			0,
			0,
			0,
			0,
			0,
			0,
			0,
			0,
			0,
			0,
			0,
			0,
			0,
			0,
			3,
			3,
			3,
			3,
			3,
			3,
			3,
			0,
			0,
			0,
			0,
			0,
			0,
			0,
			0,
			0,
			0,
			0,
			0,
			0,
			0,
			0,
			0,
			0,
			3,
			3,
			3,
			3,
			3,
			3,
			3,
			0,
			0,
			0,
			0,
			0,
			0,
			0,
			0,
			0,
			0,
			0,
			0,
			0,
			0,
			0,
			0,
			0,
			3,
			3,
			3,
			3,
			3,
			3,
			3,
			0,
			0,
			0,
			0,
			0,
			0,
			0,
			0,
			0,
			0,
			0,
			0,
			0,
			0,
			0,
			0,
			0,
			3,
			3,
			3,
			3,
			3,
			3,
			3,
			0,
			0,
			0,
			0,
			0,
			0,
			0,
			0,
			0,
			0,
			0,
			0,
			0,
			0,
			0,
			0,
			0,
			3,
			3,
			3,
			3,
			3,
			3,
			3,
			0,
			0,
			0,
			0,
			0,
			0,
			0,
			0,
			0,
			0,
			0,
			0,
			0,
			0,
			0,
			0,
			0,
			3,
			3,
			3,
			3,
			3,
			3,
			3,
			0,
			0,
			0,
			0,
			0,
			0,
			0,
			0,
			0,
			0,
			0,
			0,
			0,
			0,
			0,
			0,
			0
		]
	}
}

